datav_client/__init__.py
datav_client/datav_common_util.py
datav_client-1.1.0.10.dist-info/LICENSE
datav_client-1.1.0.10.dist-info/METADATA
datav_client-1.1.0.10.dist-info/WHEEL
datav_client-1.1.0.10.dist-info/top_level.txt
datav_client-1.1.0.10.dist-info/RECORD
